editfrontmatter/EditFrontMatter.py
editfrontmatter/__init__.py
editfrontmatter-0.0.1.dist-info/LICENSE
editfrontmatter-0.0.1.dist-info/METADATA
editfrontmatter-0.0.1.dist-info/WHEEL
editfrontmatter-0.0.1.dist-info/top_level.txt
editfrontmatter-0.0.1.dist-info/RECORD
