Metadata-Version: 2.1
Name: editfrontmatter
Version: 0.0.1
Summary: Edit front matter with Jinja2 templates
Home-page: https://karlredman.github.io/EditFrontMatter
Author: Karl N. Redman
Author-email: karl.redman@gmail.com
License: UNKNOWN
Project-URL: Source Code, http://github.com/karlredman/EditFrontMatter
Project-URL: Documentation, https://karlredman.github.io/EditFrontMatter
Keywords: jinja2 markdown front-matter
Platform: UNKNOWN
Classifier: Programming Language :: Python :: 3
Classifier: License :: OSI Approved :: MIT License
Classifier: Operating System :: OS Independent
Requires-Python: >=3.5.3
Requires-Dist: jinja2
Requires-Dist: oyaml
